wee_agent/__init__.py
wee_agent/config.py
wee_agent/errors.py
wee_agent/models.py
wee_agent/utils.py
wee_agent/wee_agent.py
wee_agent-0.1.3.dist-info/LICENSE
wee_agent-0.1.3.dist-info/METADATA
wee_agent-0.1.3.dist-info/WHEEL
wee_agent-0.1.3.dist-info/top_level.txt
wee_agent-0.1.3.dist-info/RECORD
