Metadata-Version: 2.1
Name: wee_agent
Version: 0.1.3
Summary: A micro agent for open_ai llm model
Author: Haifeng Kong
Author-email: redknox@gmail.com
Classifier: Programming Language :: Python :: 3
Classifier: License :: OSI Approved :: MIT License
Classifier: Operating System :: OS Independent
Requires-Python: >=3.10
License-File: LICENSE
Requires-Dist: jsonschema ==4.21.1
Requires-Dist: openai ==1.29.0
Requires-Dist: pydantic ==2.6.4
Requires-Dist: python-dotenv ==1.0.1
Requires-Dist: tiktoken ==0.7.0
Requires-Dist: genson ==1.2.2
